setup.cfg
setup.py
dput/__init__.py
dput/changes.py
dput/command.py
dput/config.py
dput/core.py
dput/dsc.py
dput/exceptions.py
dput/hook.py
dput/interface.py
dput/logger.py
dput/overrides.py
dput/profile.py
dput/uploader.py
dput/util.py
dput.egg-info/PKG-INFO
dput.egg-info/SOURCES.txt
dput.egg-info/dependency_links.txt
dput.egg-info/requires.txt
dput.egg-info/top_level.txt
dput/commands/__init__.py
dput/commands/breakthearchive.py
dput/commands/cancel.py
dput/commands/dm.py
dput/commands/reschedule.py
dput/commands/rm.py
dput/commands/upload.py
dput/commands/contrib/__init__.py
dput/commands/contrib/debomatic.py
dput/configs/__init__.py
dput/configs/dputcf.py
dput/configs/dputng.py
dput/hooks/__init__.py
dput/hooks/checksum.py
dput/hooks/deb.py
dput/hooks/distribution.py
dput/hooks/gpg.py
dput/hooks/impatient.py
dput/hooks/lintian.py
dput/interfaces/__init__.py
dput/interfaces/cli.py
dput/uploaders/__init__.py
dput/uploaders/ftp.py
dput/uploaders/http.py
dput/uploaders/local.py
dput/uploaders/scp.py
dput/uploaders/secure_sftp.py
dput/uploaders/sftp.py