Metadata-Version: 1.0
Name: dput
Version: 1.6
Summary: dput-ng -- like dput, but better
Home-page: UNKNOWN
Author: dput authors
Author-email: paultag@debian.org
License: GPL-2+
Platform: any
